lsfm_destripe_napari/__init__.py
lsfm_destripe_napari/_reader.py
lsfm_destripe_napari/_widget.py
lsfm_destripe_napari/_writer.py
lsfm_destripe_napari/napari.yaml
lsfm_destripe_napari/_tests/__init__.py
lsfm_destripe_napari/_tests/test_reader.py
lsfm_destripe_napari/_tests/test_widget.py
lsfm_destripe_napari/_tests/test_writer.py
destripe_lsfm-0.1.0.dist-info/LICENSE
destripe_lsfm-0.1.0.dist-info/METADATA
destripe_lsfm-0.1.0.dist-info/WHEEL
destripe_lsfm-0.1.0.dist-info/entry_points.txt
destripe_lsfm-0.1.0.dist-info/top_level.txt
destripe_lsfm-0.1.0.dist-info/RECORD
