Metadata-Version: 2.1
Name: destripe-lsfm
Version: 0.1.0
Summary: A simple plugin to destripe microscopy images
Home-page: https://github.com/MMV-Lab/destripe-lsfm
Author: Lennart Kowitz
Author-email: lennart.kowitz@isas.de
License: BSD-3-Clause
Project-URL: Bug Tracker, https://github.com/peng-Lab/lsfm_destripe_napari/issues
Project-URL: Documentation, https://github.com/peng-Lab/lsfm_destripe_napari#README.md
Project-URL: Source Code, https://github.com/peng-Lab/lsfm_destripe_napari
Project-URL: User Support, https://github.com/peng-Lab/lsfm_destripe_napari/issues
Classifier: Development Status :: 2 - Pre-Alpha
Classifier: Framework :: napari
Classifier: Intended Audience :: Developers
Classifier: License :: OSI Approved :: BSD License
Classifier: Operating System :: OS Independent
Classifier: Programming Language :: Python
Classifier: Programming Language :: Python :: 3
Classifier: Programming Language :: Python :: 3 :: Only
Classifier: Programming Language :: Python :: 3.9
Classifier: Programming Language :: Python :: 3.10
Classifier: Programming Language :: Python :: 3.11
Classifier: Topic :: Scientific/Engineering :: Image Processing
Requires-Python: >=3.9
License-File: LICENSE
Requires-Dist: numpy
Requires-Dist: qtpy
Requires-Dist: scikit-image
Requires-Dist: aicsimageio
Requires-Dist: lsfm_destripe
Provides-Extra: testing
Requires-Dist: tox; extra == "testing"
Requires-Dist: pytest; extra == "testing"
Requires-Dist: pytest-cov; extra == "testing"
Requires-Dist: pytest-qt; extra == "testing"
Requires-Dist: napari; extra == "testing"
Requires-Dist: pyqt5; extra == "testing"
